{
  "PP": {
    "price": 8850.0,
    "date": "2026-07-13",
    "source": "生意社参考价",
    "saved_at": "2026-07-14T07:21:57"
  },
  "PE": {
    "price": 7835.0,
    "date": "2026-07-13",
    "source": "生意社参考价",
    "saved_at": "2026-07-14T07:21:57"
  },
  "PC": {
    "price": 12933.33,
    "date": "2026-07-13",
    "source": "生意社参考价",
    "saved_at": "2026-07-14T07:21:57"
  },
  "ABS": {
    "price": 9483.33,
    "date": "2026-07-13",
    "source": "生意社参考价",
    "saved_at": "2026-07-14T07:21:57"
  },
  "PMMA": {
    "price": 14833.33,
    "date": "2026-07-13",
    "source": "生意社参考价",
    "saved_at": "2026-07-14T07:21:57"
  },
  "铜": {
    "price": 104420.0,
    "date": "2026-07-14",
    "source": "长江有色现货均价",
    "saved_at": "2026-07-14T07:21:57"
  },
  "铝": {
    "price": 23260.0,
    "date": "2026-07-14",
    "source": "长江有色现货均价",
    "saved_at": "2026-07-14T07:21:57"
  }
}